voxx/__init__.py
voxx/__main__.py
voxx/connection.py
voxx/model.py
voxx/tui.py
voxx/css/tui.css
voxx_cli-1.0.9.dist-info/METADATA
voxx_cli-1.0.9.dist-info/WHEEL
voxx_cli-1.0.9.dist-info/dependency_links.txt
voxx_cli-1.0.9.dist-info/entry_points.txt
voxx_cli-1.0.9.dist-info/top_level.txt
voxx_cli-1.0.9.dist-info/RECORD
