Metadata-Version: 2.1
Name: voxx-cli
Version: 1.0.9
Summary: A command line interface client for Voxx
Home-page: https://github.com/CyR1en/voxx-client-cli
Download-URL: https://github.com/CyR1en/voxx-client-cli
Author: CyR1en
Author-email: ethan.bacurio@ucdenver.edu
License: MIT
Classifier: License :: OSI Approved :: MIT License
Classifier: Programming Language :: Python :: 3.7
Requires-Python: >=3.7
Requires-Dist: textual (~=0.22.3)
Requires-Dist: rich (~=13.3.5)
